mtc_token_healing-0.3.1.dist-info/METADATA
mtc_token_healing-0.3.1.dist-info/WHEEL
mtc_token_healing/__init__.py
mtc_token_healing/mtc_token_healing.abi3.so
mtc_token_healing/mtc_token_healing.pyi
mtc_token_healing-0.3.1.dist-info/RECORD
